{
    "station": {
        "usgsId": "",
        "wrId": "18028",
        "usgsName": "",
        "wrName": "James River at New Canton",
        "wrIsActive": true,
        "usgsDescription": "",
        "wrDescription": "This site is monitored by James River Association volunteers.",
        "recordTime": "2020-09-10T00:36:28+0000",
        "locationStatus": "Danger"
    },
    "data": {
        "bacteriaThreshold": {
            "date": "2020-09-03T13:28:51.559831",
            "value": "0",
            "safety": "Fair"
        },
        "waterTempC": {
            "date": "2020-09-03T13:28:51.559831",
            "value": "26.5",
            "safety": "Caution"
        },
        "eColiConcentration": {
            "date": "2020-09-03T13:28:51.559831",
            "value": "200",
            "safety": "Danger"
        },
        "streamFlow": {
            "date": "",
            "value": "N.A.",
            "safety": "N.A."
        },
        "gaugeHeight": {
            "date": "",
            "value": "N.A.",
            "safety": "N.A."
        }
    }
}